<graph id="Graph">
  <version>1.0</version>
  <node id="Read">
    <operator>Read</operator>
    <sources/>
    <parameters class="com.bc.ceres.binding.dom.XppDomElement">
      <file>${inputFile}</file>
    </parameters>
  </node>
  <node id="SnaphuExport">
    <operator>SnaphuExport</operator>
    <sources>
      <sourceProduct refid="Read"/>
    </sources>
    <parameters class="com.bc.ceres.binding.dom.XppDomElement">
      <targetFolder>${outputFolder_unwrapped_interferograms}</targetFolder>
      <statCostMode>DEFO</statCostMode>
      <initMethod>MCF</initMethod>
      <numberOfTileRows>1</numberOfTileRows>
      <numberOfTileCols>1</numberOfTileCols>
      <numberOfProcessors>4</numberOfProcessors>
      <rowOverlap>200</rowOverlap>
      <colOverlap>200</colOverlap>
      <tileCostThreshold>500</tileCostThreshold>
    </parameters>
  </node>
  <applicationData id="Presentation">
    <Description/>
    <node id="Read">
            <displayPosition x="37.0" y="134.0"/>
    </node>
    <node id="SnaphuExport">
      <displayPosition x="291.0" y="131.0"/>
    </node>
  </applicationData>
</graph>